pssl/__init__.py
pssl/config.py
pssl/loss.py
pssl/architecture/__init__.py
pssl/architecture/mlp.py
pssl/auxillary/__init__.py
pssl/auxillary/initialization.py
pssl/auxillary/linalg.py
pssl/auxillary/optimization.py
pssl/auxillary/plots.py
pssl/datasets/__init__.py
pssl/datasets/halfmoon.py
pssl-0.0.2.dist-info/LICENSE
pssl-0.0.2.dist-info/METADATA
pssl-0.0.2.dist-info/WHEEL
pssl-0.0.2.dist-info/top_level.txt
pssl-0.0.2.dist-info/RECORD
