Metadata-Version: 2.1
Name: pssl
Version: 0.0.2
Summary: Research library to investigate principles behind self-supervised learning.
Author-email: Vivien Cabannes <vivc@meta.com>
Project-URL: Homepage, https://github.com/facebookresearch/PSSL
Project-URL: Bug Tracker, https://github.com/facebookresearch/PSSL/issues
Classifier: Programming Language :: Python :: 3
Classifier: License :: OSI Approved :: MIT License
Classifier: Operating System :: OS Independent
Requires-Python: >=3.7
License-File: LICENSE
